e3dc_cli-1.0.5.dist-info/METADATA
e3dc_cli-1.0.5.dist-info/WHEEL
e3dc_cli-1.0.5.dist-info/entry_points.txt
e3dc_cli-1.0.5.dist-info/licenses/LICENSE
e3dc_cli/__init__.py
e3dc_cli/__main__.py
e3dc_cli/argparse.py
e3dc_cli/connection.py
e3dc_cli/output.py
e3dc_cli/query.py
e3dc_cli/setter.py
e3dc_cli-1.0.5.dist-info/RECORD
