Metadata-Version: 2.1
Name: e3dc-cli
Version: 1.0.5
Summary: Command-line tool to query E3/DC systems
Author-Email: Sebastian Waldvogel <sebastian@waldvogels.de>
License: MIT
Project-URL: Repository, https://github.com/waldbaer/e3dc-cli
Requires-Python: >=3.10
Requires-Dist: pye3dc==0.10.0
Requires-Dist: tzlocal==5.3.1
Requires-Dist: jsonargparse==4.42.0
Requires-Dist: rich-argparse==1.7.2
Requires-Dist: pydantic==2.12.5
